evalops/__init__.py
evalops/huggingface_loader.py
evalops/main.py
evalops/wrapper.py
evalops-0.0.6.dist-info/LICENSE
evalops-0.0.6.dist-info/METADATA
evalops-0.0.6.dist-info/WHEEL
evalops-0.0.6.dist-info/RECORD
