Metadata-Version: 2.1
Name: evalops
Version: 0.0.6
Summary: evalops - TGSC
Home-page: https://github.com/The-Swarm-Corporation/StatisticalModelEvaluator
License: MIT
Keywords: artificial intelligence,deep learning,optimizers,Prompt Engineering
Author: Kye Gomez
Author-email: kye@apac.ai
Requires-Python: >=3.10,<4.0
Classifier: Development Status :: 4 - Beta
Classifier: Intended Audience :: Developers
Classifier: License :: OSI Approved :: MIT License
Classifier: Programming Language :: Python :: 3
Classifier: Programming Language :: Python :: 3.10
Classifier: Programming Language :: Python :: 3.11
Classifier: Programming Language :: Python :: 3.12
Classifier: Programming Language :: Python :: 3.9
Classifier: Topic :: Scientific/Engineering :: Artificial Intelligence
Requires-Dist: datasets
Requires-Dist: difflib
Requires-Dist: loguru
Requires-Dist: numpy
Requires-Dist: pandas
Requires-Dist: pydantic
Requires-Dist: scipy
Project-URL: Documentation, https://github.com/The-Swarm-Corporation/StatisticalModelEvaluator
Project-URL: Repository, https://github.com/The-Swarm-Corporation/StatisticalModelEvaluator
